Workbook

Sheet Assumption
B3: Assumptions
B5: A | C5: B
B6: Revenue & Sales Drivers
B7: Avg Selling Price | C7: 50
B8: Units Sold per Month | C8: 1000
B9: Annual Discount % (Seasonal) | C9: 0.05
B11: Cost Drivers
B12: Cost per Unit (COGS) | C12: 30
B13: Return/Refund Rate % | C13: 0.02
B15: Operating Expenses
B16: Marketing Expense per Month | C16: 5000
B17: Salary Expense per Month | C17: 20000
B18: Rent per Month | C18: 8000
B20: Other Assumptions
B21: Tax Rate | C21: 0.2

Sheet Budgeting
B2: Budgeting Table
B5: Month | C5: Units Sold | D5: Selling Price | E5: Gross Revenue | F5: Discount | G5: Net Revenue | H5: Returns (2%) | I5: Final Revenue | J5: COGS | K5: Gross Profit | L5: Operating Expenses | M5: Operating Profit | N5: Tax (20%) | O5: Net Profit
B6: Jan | C6: =Assumption!$C$8 -> 1000 | D6: =Assumption!$C$7 -> 50 | E6: =C6*D6 -> 50000 | F6: =E6*(5%/12) -> 208.33333 | G6: =E6-F6 -> 49791.667 | H6: =G6*2% -> 995.83333 | I6: =G6-H6 -> 48795.833 | J6: =C6*Assumption!$C$12 -> 30000 | K6: =I6-J6 -> 18795.833 | L6: =Assumption!$C$16+Assumption!$C$17+Assumption!$C$18 -> 33000 | M6: =K6-L6 -> -14204.167 | N6: =IF(L6<0, L6*20%,0) -> 0 | O6: =M6-N6 -> -14204.167
B7: Feb | C7: =Assumption!$C$8 -> 1000 | D7: =Assumption!$C$7 -> 50 | E7: =C7*D7 -> 50000 | F7: =E7*(5%/12) -> 208.33333 | G7: =E7-F7 -> 49791.667 | H7: =G7*2% -> 995.83333 | I7: =G7-H7 -> 48795.833 | J7: =C7*Assumption!$C$12 -> 30000 | K7: =I7-J7 -> 18795.833 | L7: =Assumption!$C$16+Assumption!$C$17+Assumption!$C$18 -> 33000 | M7: =K7-L7 -> -14204.167 | N7: =IF(L7<0, L7*20%,0) -> 0 | O7: =M7-N7 -> -14204.167
B8: Mar | C8: =Assumption!$C$8 -> 1000 | D8: =Assumption!$C$7 -> 50 | E8: =C8*D8 -> 50000 | F8: =E8*(5%/12) -> 208.33333 | G8: =E8-F8 -> 49791.667 | H8: =G8*2% -> 995.83333 | I8: =G8-H8 -> 48795.833 | J8: =C8*Assumption!$C$12 -> 30000 | K8: =I8-J8 -> 18795.833 | L8: =Assumption!$C$16+Assumption!$C$17+Assumption!$C$18 -> 33000 | M8: =K8-L8 -> -14204.167 | N8: =IF(L8<0, L8*20%,0) -> 0 | O8: =M8-N8 -> -14204.167
B9: Apr | C9: =Assumption!$C$8 -> 1000 | D9: =Assumption!$C$7 -> 50 | E9: =C9*D9 -> 50000 | F9: =E9*(5%/12) -> 208.33333 | G9: =E9-F9 -> 49791.667 | H9: =G9*2% -> 995.83333 | I9: =G9-H9 -> 48795.833 | J9: =C9*Assumption!$C$12 -> 30000 | K9: =I9-J9 -> 18795.833 | L9: =Assumption!$C$16+Assumption!$C$17+Assumption!$C$18 -> 33000 | M9: =K9-L9 -> -14204.167 | N9: =IF(L9<0, L9*20%,0) -> 0 | O9: =M9-N9 -> -14204.167
B10: May | C10: =Assumption!$C$8 -> 1000 | D10: =Assumption!$C$7 -> 50 | E10: =C10*D10 -> 50000 | F10: =E10*(5%/12) -> 208.33333 | G10: =E10-F10 -> 49791.667 | H10: =G10*2% -> 995.83333 | I10: =G10-H10 -> 48795.833 | J10: =C10*Assumption!$C$12 -> 30000 | K10: =I10-J10 -> 18795.833 | L10: =Assumption!$C$16+Assumption!$C$17+Assumption!$C$18 -> 33000 | M10: =K10-L10 -> -14204.167 | N10: =IF(L10<0, L10*20%,0) -> 0 | O10: =M10-N10 -> -14204.167
B11: Jun | C11: =Assumption!$C$8 -> 1000 | D11: =Assumption!$C$7 -> 50 | E11: =C11*D11 -> 50000 | F11: =E11*(5%/12) -> 208.33333 | G11: =E11-F11 -> 49791.667 | H11: =G11*2% -> 995.83333 | I11: =G11-H11 -> 48795.833 | J11: =C11*Assumption!$C$12 -> 30000 | K11: =I11-J11 -> 18795.833 | L11: =Assumption!$C$16+Assumption!$C$17+Assumption!$C$18 -> 33000 | M11: =K11-L11 -> -14204.167 | N11: =IF(L11<0, L11*20%,0) -> 0 | O11: =M11-N11 -> -14204.167
B12: Jul | C12: =Assumption!$C$8 -> 1000 | D12: =Assumption!$C$7 -> 50 | E12: =C12*D12 -> 50000 | F12: =E12*(5%/12) -> 208.33333 | G12: =E12-F12 -> 49791.667 | H12: =G12*2% -> 995.83333 | I12: =G12-H12 -> 48795.833 | J12: =C12*Assumption!$C$12 -> 30000 | K12: =I12-J12 -> 18795.833 | L12: =Assumption!$C$16+Assumption!$C$17+Assumption!$C$18 -> 33000 | M12: =K12-L12 -> -14204.167 | N12: =IF(L12<0, L12*20%,0) -> 0 | O12: =M12-N12 -> -14204.167
B13: Aug | C13: =Assumption!$C$8 -> 1000 | D13: =Assumption!$C$7 -> 50 | E13: =C13*D13 -> 50000 | F13: =E13*(5%/12) -> 208.33333 | G13: =E13-F13 -> 49791.667 | H13: =G13*2% -> 995.83333 | I13: =G13-H13 -> 48795.833 | J13: =C13*Assumption!$C$12 -> 30000 | K13: =I13-J13 -> 18795.833 | L13: =Assumption!$C$16+Assumption!$C$17+Assumption!$C$18 -> 33000 | M13: =K13-L13 -> -14204.167 | N13: =IF(L13<0, L13*20%,0) -> 0 | O13: =M13-N13 -> -14204.167
B14: Sep | C14: =Assumption!$C$8 -> 1000 | D14: =Assumption!$C$7 -> 50 | E14: =C14*D14 -> 50000 | F14: =E14*(5%/12) -> 208.33333 | G14: =E14-F14 -> 49791.667 | H14: =G14*2% -> 995.83333 | I14: =G14-H14 -> 48795.833 | J14: =C14*Assumption!$C$12 -> 30000 | K14: =I14-J14 -> 18795.833 | L14: =Assumption!$C$16+Assumption!$C$17+Assumption!$C$18 -> 33000 | M14: =K14-L14 -> -14204.167 | N14: =IF(L14<0, L14*20%,0) -> 0 | O14: =M14-N14 -> -14204.167
B15: Oct | C15: =Assumption!$C$8 -> 1000 | D15: =Assumption!$C$7 -> 50 | E15: =C15*D15 -> 50000 | F15: =E15*(5%/12) -> 208.33333 | G15: =E15-F15 -> 49791.667 | H15: =G15*2% -> 995.83333 | I15: =G15-H15 -> 48795.833 | J15: =C15*Assumption!$C$12 -> 30000 | K15: =I15-J15 -> 18795.833 | L15: =Assumption!$C$16+Assumption!$C$17+Assumption!$C$18 -> 33000 | M15: =K15-L15 -> -14204.167 | N15: =IF(L15<0, L15*20%,0) -> 0 | O15: =M15-N15 -> -14204.167
B16: Nov | C16: =Assumption!$C$8 -> 1000 | D16: =Assumption!$C$7 -> 50 | E16: =C16*D16 -> 50000 | F16: =E16*(5%/12) -> 208.33333 | G16: =E16-F16 -> 49791.667 | H16: =G16*2% -> 995.83333 | I16: =G16-H16 -> 48795.833 | J16: =C16*Assumption!$C$12 -> 30000 | K16: =I16-J16 -> 18795.833 | L16: =Assumption!$C$16+Assumption!$C$17+Assumption!$C$18 -> 33000 | M16: =K16-L16 -> -14204.167 | N16: =IF(L16<0, L16*20%,0) -> 0 | O16: =M16-N16 -> -14204.167
B17: Dec | C17: =Assumption!$C$8 -> 1000 | D17: =Assumption!$C$7 -> 50 | E17: =C17*D17 -> 50000 | F17: =E17*(5%/12) -> 208.33333 | G17: =E17-F17 -> 49791.667 | H17: =G17*2% -> 995.83333 | I17: =G17-H17 -> 48795.833 | J17: =C17*Assumption!$C$12 -> 30000 | K17: =I17-J17 -> 18795.833 | L17: =Assumption!$C$16+Assumption!$C$17+Assumption!$C$18 -> 33000 | M17: =K17-L17 -> -14204.167 | N17: =IF(L17<0, L17*20%,0) -> 0 | O17: =M17-N17 -> -14204.167

Sheet Actuals
B2: Actuals
B4: Month | C4: Budgeted Net Reveue | D4: Actual Revenue | E4: Revenue Variance | F4: Rev Var(%) | G4: Budget N.P | H4: Actual Net Profit | I4: Profit Variance | J4: Profit var %
B5: Jan | C5: =Budgeting!$G$6 -> 49791.667 | D5: 50500 | E5: =D5-C5 -> 708.33333 | F5: =(D5-C5)/C5 -> 0.014225941 | G5: =Budgeting!$M$6 -> -14204.167 | H5: -13900 | I5: =H5-G5 -> 304.16667 | J5: =I5/ABS(G5) -> 0.021413904
B6: Feb | C6: =Budgeting!$G$6 -> 49791.667 | D6: 49000 | E6: =D6-C6 -> -791.66667 | F6: =(D6-C6)/C6 -> -0.015899582 | G6: =Budgeting!$M$6 -> -14204.167 | H6: -15200 | I6: =H6-G6 -> -995.83333 | J6: =I6/ABS(G6) -> -0.070108536
B7: Mar | C7: =Budgeting!$G$6 -> 49791.667 | D7: 51200 | E7: =D7-C7 -> 1408.3333 | F7: =(D7-C7)/C7 -> 0.028284519 | G7: =Budgeting!$M$6 -> -14204.167 | H7: -12800 | I7: =H7-G7 -> 1404.1667 | J7: =I7/ABS(G7) -> 0.098855969
B8: Apr | C8: =Budgeting!$G$6 -> 49791.667 | D8: 52000 | E8: =D8-C8 -> 2208.3333 | F8: =(D8-C8)/C8 -> 0.044351464 | G8: =Budgeting!$M$6 -> -14204.167 | H8: -12500 | I8: =H8-G8 -> 1704.1667 | J8: =I8/ABS(G8) -> 0.11997653
B9: May | C9: =Budgeting!$G$6 -> 49791.667 | D9: 47500 | E9: =D9-C9 -> -2291.6667 | F9: =(D9-C9)/C9 -> -0.046025105 | G9: =Budgeting!$M$6 -> -14204.167 | H9: -16000 | I9: =H9-G9 -> -1795.8333 | J9: =I9/ABS(G9) -> -0.12643004
B10: Jun | C10: =Budgeting!$G$6 -> 49791.667 | D10: 48200 | E10: =D10-C10 -> -1591.6667 | F10: =(D10-C10)/C10 -> -0.031966527 | G10: =Budgeting!$M$6 -> -14204.167 | H10: -15300 | I10: =H10-G10 -> -1095.8333 | J10: =I10/ABS(G10) -> -0.077148724
B11: Jul | C11: =Budgeting!$G$6 -> 49791.667 | D11: 49700 | E11: =D11-C11 -> -91.666667 | F11: =(D11-C11)/C11 -> -0.0018410042 | G11: =Budgeting!$M$6 -> -14204.167 | H11: -14200 | I11: =H11-G11 -> 4.1666667 | J11: =I11/ABS(G11) -> 0.00029334116
B12: Aug | C12: =Budgeting!$G$6 -> 49791.667 | D12: 51100 | E12: =D12-C12 -> 1308.3333 | F12: =(D12-C12)/C12 -> 0.026276151 | G12: =Budgeting!$M$6 -> -14204.167 | H12: -13100 | I12: =H12-G12 -> 1104.1667 | J12: =I12/ABS(G12) -> 0.077735406
B13: Sep | C13: =Budgeting!$G$6 -> 49791.667 | D13: 52500 | E13: =D13-C13 -> 2708.3333 | F13: =(D13-C13)/C13 -> 0.054393305 | G13: =Budgeting!$M$6 -> -14204.167 | H13: -12600 | I13: =H13-G13 -> 1604.1667 | J13: =I13/ABS(G13) -> 0.11293634
B14: Oct | C14: =Budgeting!$G$6 -> 49791.667 | D14: 50900 | E14: =D14-C14 -> 1108.3333 | F14: =(D14-C14)/C14 -> 0.022259414 | G14: =Budgeting!$M$6 -> -14204.167 | H14: -13600 | I14: =H14-G14 -> 604.16667 | J14: =I14/ABS(G14) -> 0.042534468
B15: Nov | C15: =Budgeting!$G$6 -> 49791.667 | D15: 49300 | E15: =D15-C15 -> -491.66667 | F15: =(D15-C15)/C15 -> -0.009874477 | G15: =Budgeting!$M$6 -> -14204.167 | H15: -15000 | I15: =H15-G15 -> -795.83333 | J15: =I15/ABS(G15) -> -0.056028161
B16: Dec | C16: =Budgeting!$G$6 -> 49791.667 | D16: 52300 | E16: =D16-C16 -> 2508.3333 | F16: =(D16-C16)/C16 -> 0.050376569 | G16: =Budgeting!$M$6 -> -14204.167 | H16: -12400 | I16: =H16-G16 -> 1804.1667 | J16: =I16/ABS(G16) -> 0.12701672
B18: YTD | C18: =SUM(C5:C16) -> 597500 | D18: =SUM(D5:D16) -> 604200

Sheet KPIs
B2: Budget VS Actual Net Revenue | J2: YTD BUDGET VS ACTUAL NET REVENUE | R2: Budget vs Actual Net Profit
B21: Act VS BUD Revenue Variance (%) | J21: Profit Variance | R21: Profit Variance
